Metadata-Version: 2.1
Name: cc-api-helper
Version: 2.1.0
Author: 
Author-email: 
License: MIT
Requires-Python: >=3.7
Requires-Dist: requests
